silicium
