Metadata-Version: 2.1
Name: silicium
Version: 0.1.4
Summary: Silicium is an ahead-of-time interpreted all-language compiler in Python.
Home-page: https://github.com/SamimiesGames/silicium
Author: Samimies
License: MIT
Platform: UNKNOWN
License-File: LICENSE
